pyserilog_sinks_console/__init__.py
pyserilog_sinks_console/console_sink.py
pyserilog_sinks_console/extensions.py
pyserilog_sinks_console/formatting/formatter_utils.py
pyserilog_sinks_console/formatting/themed_display_value_formatter.py
pyserilog_sinks_console/formatting/themed_json_value_formatter.py
pyserilog_sinks_console/formatting/themed_value_formatter.py
pyserilog_sinks_console/formatting/themed_value_formatter_state.py
pyserilog_sinks_console/output/__init__.py
pyserilog_sinks_console/output/event_property_token_renderer.py
pyserilog_sinks_console/output/exception_token_renderer.py
pyserilog_sinks_console/output/level_token_renderer.py
pyserilog_sinks_console/output/message_template_output_token_renderer.py
pyserilog_sinks_console/output/new_line_token_renderer.py
pyserilog_sinks_console/output/output_template_renderer.py
pyserilog_sinks_console/output/output_template_token_renderer.py
pyserilog_sinks_console/output/properties_token_renderer.py
pyserilog_sinks_console/output/text_token_renderer.py
pyserilog_sinks_console/output/timestamp_token_renderer.py
pyserilog_sinks_console/rendering/alignment_extensions.py
pyserilog_sinks_console/rendering/themed_message_template_renderer.py
pyserilog_sinks_console/themes/__init__.py
pyserilog_sinks_console/themes/ansi_console_theme.py
pyserilog_sinks_console/themes/console_theme.py
pyserilog_sinks_console/themes/console_theme_style.py
pyserilog_sinks_console/themes/empty_console.py
pyserilog_sinks_console/themes/istyle_reset.py
pyserilog_sinks_console/themes/style_reset.py
pyserilog_sinks_console/themes/system_console_theme.py
pyserilog_sinks_console/themes/system_console_themes.py
pyserilog_sinks_console-0.1.0.dist-info/LICENSE
pyserilog_sinks_console-0.1.0.dist-info/METADATA
pyserilog_sinks_console-0.1.0.dist-info/WHEEL
pyserilog_sinks_console-0.1.0.dist-info/top_level.txt
pyserilog_sinks_console-0.1.0.dist-info/RECORD
