Metadata-Version: 2.1
Name: pyserilog-sinks-console
Version: 0.1.0
Summary: python version of serilog a structured logging library
Author: Reza Sadeghi
Author-email: rezasadeghikhas@gmail.com
License: Apache2
Classifier: Development Status :: 3 - Alpha
Classifier: Intended Audience :: Developers
Classifier: Topic :: System :: Logging
Classifier: Topic :: Software Development :: Libraries
Classifier: Topic :: Internet :: Log Analysis
Classifier: License :: OSI Approved :: Apache Software License
Classifier: Programming Language :: Python :: 3.11
Requires: colorama
Requires: pyserilog
License-File: LICENSE
Requires-Dist: pyserilog (>=0.2.0)
Requires-Dist: colorama (>=0.4.6)
